styxdocker/__init__.py
styxdocker-0.5.1.dist-info/WHEEL
styxdocker-0.5.1.dist-info/METADATA
styxdocker-0.5.1.dist-info/RECORD
